AioFastGet/__init__.py
AioFastGet/__version__.py
AioFastGet/core.py
AioFastGet-0.0.7.dist-info/LICENSE
AioFastGet-0.0.7.dist-info/METADATA
AioFastGet-0.0.7.dist-info/WHEEL
AioFastGet-0.0.7.dist-info/top_level.txt
AioFastGet-0.0.7.dist-info/RECORD
