Metadata-Version: 2.1
Name: AioFastGet
Version: 0.0.7
Summary: AsyncioFastGetFrame
Home-page: https://github.com/me/myproject
Author: dalyer
Author-email: 954742660@qq.com
License: MIT
Platform: UNKNOWN
Classifier: License :: OSI Approved :: MIT License
Classifier: Programming Language :: Python
Classifier: Programming Language :: Python :: 3
Classifier: Programming Language :: Python :: 3.6
Classifier: Programming Language :: Python :: 3.7
Classifier: Programming Language :: Python :: 3.8
Classifier: Programming Language :: Python :: 3.9
Classifier: Programming Language :: Python :: Implementation :: CPython
Classifier: Programming Language :: Python :: Implementation :: PyPy
Requires-Python: >=3.5.0
License-File: LICENSE
Requires-Dist: aioredis (==1.3.1)
Requires-Dist: aiohttp (==3.8.1)
Requires-Dist: cchardet (==2.1.7)
